README.md
setup.cfg
setup.py
basic_distribution_extension/Binomialdistribution.py
basic_distribution_extension/Gaussiandistribution.py
basic_distribution_extension/Generaldistribution.py
basic_distribution_extension/__init__.py
basic_distribution_extension.egg-info/PKG-INFO
basic_distribution_extension.egg-info/SOURCES.txt
basic_distribution_extension.egg-info/dependency_links.txt
basic_distribution_extension.egg-info/not-zip-safe
basic_distribution_extension.egg-info/top_level.txt