Metadata-Version: 1.0
Name: basic-distribution-extension
Version: 0.1
Summary: Extension for Gaussian and Binomial distributions
Home-page: UNKNOWN
Author: UNKNOWN
Author-email: elleoyj@gmail.com
License: UNKNOWN
Platform: UNKNOWN
